MorfDict-0.4.7.dist-info/DESCRIPTION.rst
MorfDict-0.4.7.dist-info/METADATA
MorfDict-0.4.7.dist-info/RECORD
MorfDict-0.4.7.dist-info/WHEEL
MorfDict-0.4.7.dist-info/metadata.json
MorfDict-0.4.7.dist-info/top_level.txt
morfdict/README.rst
morfdict/__init__.py
morfdict/factory.py
morfdict/models.py
morfdict/tests/__init__.py
morfdict/tests/base.py
morfdict/tests/factory.py
morfdict/tests/morfdict.py
