Metadata-Version: 2.0
Name: MorfDict
Version: 0.4.7
Summary: MorfDict is a dict like object, which convers data on the fly.
Home-page: UNKNOWN
Author: Dominik "Socek" Długajczy
Author-email: msocek@gmail.com
License: UNKNOWN
Platform: UNKNOWN
